postmark_inbound/__init__.py
python_postmark_inbound-1.1.0.dist-info/DESCRIPTION.rst
python_postmark_inbound-1.1.0.dist-info/METADATA
python_postmark_inbound-1.1.0.dist-info/metadata.json
python_postmark_inbound-1.1.0.dist-info/pbr.json
python_postmark_inbound-1.1.0.dist-info/RECORD
python_postmark_inbound-1.1.0.dist-info/top_level.txt
python_postmark_inbound-1.1.0.dist-info/WHEEL
