Metadata-Version: 2.0
Name: python-postmark-inbound
Version: 1.1.0
Summary: Python wrapper for Postmark Inbound
Home-page: https://github.com/jpadilla/postmark-inbound-python
Author: José Padilla
Author-email: hello@jpadilla.com
License: MIT
Platform: UNKNOWN
Classifier: Programming Language :: Python
Classifier: Programming Language :: Python :: 2
Classifier: Programming Language :: Python :: 2.7
Classifier: Programming Language :: Python :: 3
Classifier: Programming Language :: Python :: 3.3
Classifier: Programming Language :: Python :: 3.4
